{
    "sequence": [
        "MB5L",
        "MB6L",
        "MB7L",
        "ZH1L",
        "ZV1L",
        "MB8L",
        "MB9L",
        "MB10L",
        "ZV2L",
        "ZH2L",
        "MB11L",
        "ML1L",
        "ML2L",
        "ZV3L",
        "ZH3L",
        "ML3L",
        "ZH4L",
        "ZV4L",
        "ZH5L",
        "ZV5L",
        "ML4L",
        "ZH6L",
        "ZV6L",
        "ML5L",
        "ZH7L",
        "ZV7L",
        "ML6L",
        "ZH8L",
        "ZV8L",
        "ML7L",
        "ZH9L",
        "ML8L",
        "ZV9L",
        "ML9L",
        "ZH10L",
        "ML10L",
        "ZV10L",
        "ML11L",
        "ZH11L",
        "ML12L",
        "ZV11L",
        "ML13L",
        "ZH12L",
        "ML14L",
        "ZV12L",
        "ML15L",
        "ZX10T",
        "ZX11T",
        "ML1T",
        "ZV13L",
        "ZX12T",
        "ML2T",
        "ZY20T",
        "ZY21T",
        "ML101T",
        "ML102T",
        "ZY22T",
        "ZY23T",
        "ML103T",
        "ZX30T",
        "ML3T",
        "ZX31T",
        "ZV30T",
        "ZH30T",
        "ML104T",
        "ZX32T",
        "ML4T",
        "ML105T",
        "ZV40T",
        "ZH40T",
        "ML5T",
        "ML6T",
        "ZX50T",
        "ML106T",
        "ZX50T",
        "ML7T",
        "ZX51T",
        "ZV50T",
        "ML8T",
        "ZH50T",
        "ZV51T",
        "ML9T",
        "MB10T",
        "MB11T"
    ],
    "correctors": {
        "names": [
            "ZH1L",
            "ZV1L",
            "ZV2L",
            "ZH2L",
            "ZV3L",
            "ZH3L",
            "ZH4L",
            "ZV4L",
            "ZH5L",
            "ZV5L",
            "ZH6L",
            "ZV6L",
            "ZH7L",
            "ZV7L",
            "ZH8L",
            "ZV8L",
            "ZH9L",
            "ZV9L",
            "ZH10L",
            "ZV10L",
            "ZH11L",
            "ZV11L",
            "ZH12L",
            "ZV12L",
            "ZX10T",
            "ZX11T",
            "ZV13L",
            "ZX12T",
            "ZY20T",
            "ZY21T",
            "ZY22T",
            "ZY23T",
            "ZX30T",
            "ZX31T",
            "ZV30T",
            "ZH30T",
            "ZX32T",
            "ZV40T",
            "ZH40T",
            "ZX50T",
            "ZX50T",
            "ZX51T",
            "ZV50T",
            "ZH50T",
            "ZV51T"
        ],
        "bdes": [
            1.6058,
            0.32324,
            -3.694e-05,
            -0.05,
            -0.018255,
            -0.0023425,
            -0.63212,
            -0.51377,
            0.0067611,
            0.025597,
            -0.089344,
            -0.23399,
            -0.34279,
            0.0008922,
            0.095066,
            -0.1336,
            -0.39271,
            -0.072191,
            -0.21644,
            -0.41065,
            0.09808,
            0.37969,
            0.043499,
            -1.4308,
            -0.5,
            0.81,
            -0.69,
            0.9,
            0.34,
            -0.25,
            -1.26,
            -1.47,
            0.0,
            0.0,
            0.09,
            -1.79,
            2.05,
            -1.5,
            -2.1085,
            1.29,
            1.29,
            -1.7,
            0.38,
            1.35,
            0.08
        ],
        "bact": [
            1.6047874689102173,
            0.3224230408668518,
            -0.00488519761711359,
            -0.05373717471957207,
            -0.02198338881134987,
            -0.00488519761711359,
            -0.6350756883621216,
            -0.5178309679031372,
            0.00488519761711359,
            0.024425989016890526,
            -0.09281875938177109,
            -0.23693208396434784,
            -0.3468490242958069,
            0.0,
            0.09281875938177109,
            -0.13678553700447083,
            -0.39570102095603943,
            -0.07572057098150253,
            -0.21983389556407928,
            -0.4152418076992035,
            0.0977039560675621,
            0.3786028325557709,
            0.04152418300509453,
            -1.4338055849075317,
            -0.5080605745315552,
            0.8036150336265564,
            -0.6985832452774048,
            0.898876428604126,
            0.33463606238365173,
            -0.2589154839515686,
            -1.2677088975906372,
            -1.4802148342132568,
            0.0,
            0.0,
            0.08304836601018906,
            -1.797752857208252,
            2.044455051422119,
            -1.5095261335372925,
            -2.1128480434417725,
            1.2848069667816162,
            1.2848069667816162,
            -1.7073765993118286,
            0.37371763586997986,
            1.343429446220398,
            0.07572057098150253
        ]
    },
    "bpms": {
        "names": [
            "MB5L",
            "MB6L",
            "MB7L",
            "MB8L",
            "MB9L",
            "MB10L",
            "MB11L",
            "ML1L",
            "ML2L",
            "ML3L",
            "ML4L",
            "ML5L",
            "ML6L",
            "ML7L",
            "ML8L",
            "ML9L",
            "ML10L",
            "ML11L",
            "ML12L",
            "ML13L",
            "ML14L",
            "ML15L",
            "ML1T",
            "ML2T",
            "ML101T",
            "ML102T",
            "ML103T",
            "ML3T",
            "ML104T",
            "ML4T",
            "ML105T",
            "ML5T",
            "ML6T",
            "ML106T",
            "ML7T",
            "ML8T",
            "ML9T",
            "MB10T",
            "MB11T"
        ],
        "x": [
            [
                -1.123738408088684,
                0.6372624635696411,
                0.15048471093177795,
                -7.936893463134766,
                1.4499967098236084,
                1.1794276237487793,
                0.04339107125997543,
                -2.4774527549743652,
                -1.095827341079712,
                0.301939457654953,
                -0.1689220517873764,
                -0.294759064912796,
                0.49095532298088074,
                -1.269168734550476,
                0.45444899797439575,
                -6.266749382019043,
                -2.3492777347564697,
                -0.7107909917831421,
                -1.2226293087005615,
                -0.3886486291885376,
                -0.7628881335258484,
                -1.1714539527893066,
                -6.578082084655762,
                0.5203707218170166,
                -4.692979335784912,
                1.7372969388961792,
                0.8802585601806641,
                -0.5768167972564697,
                -1.1354793310165405,
                -6.402421951293945,
                -7.042582035064697,
                -2.8493831157684326,
                1.1090441942214966,
                -5.104370594024658,
                -1.230724811553955,
                -2.042165756225586,
                -3.901625394821167,
                2.800302505493164,
                -3.2185823917388916
            ],
            [
                -1.1565914154052734,
                0.6208595633506775,
                0.13393202424049377,
                -7.922267436981201,
                1.4696637392044067,
                1.192147135734558,
                0.035079024732112885,
                -2.468714714050293,
                -1.1002997159957886,
                0.2830890715122223,
                -0.15045684576034546,
                -0.5246812105178833,
                0.5004712343215942,
                -1.35469388961792,
                0.452216774225235,
                -6.144926071166992,
                -2.312467575073242,
                -0.7649356126785278,
                -1.2960920333862305,
                -0.43064257502555847,
                -0.7950612902641296,
                -1.2125349044799805,
                -6.587343692779541,
                0.38063210248947144,
                -4.804565906524658,
                1.8284056186676025,
                0.8536189198493958,
                -0.6620678305625916,
                -1.211958885192871,
                -6.294367790222168,
                -7.171302795410156,
                -2.8551371097564697,
                0.4374501705169678,
                -5.134541988372803,
                -1.3022332191467285,
                -2.0311648845672607,
                -4.024144172668457,
                2.849985122680664,
                -3.3121583461761475
            ],
            [
                -1.1574761867523193,
                0.67141193151474,
                0.13276410102844238,
                -7.988729000091553,
                1.4435516595840454,
                1.1346580982208252,
                0.017937492579221725,
                -2.527503252029419,
                -1.0146394968032837,
                0.35682398080825806,
                -0.11184492707252502,
                -0.5449318289756775,
                0.5326519012451172,
                -1.3651411533355713,
                0.5212836861610413,
                -6.2862677574157715,
                -2.464627504348755,
                -0.7320933938026428,
                -1.2931965589523315,
                -0.3667742908000946,
                -0.68108069896698,
                -1.2030552625656128,
                -6.590637683868408,
                0.5445942282676697,
                -4.720136642456055,
                1.8532904386520386,
                0.9172313213348389,
                -0.6821788549423218,
                -1.1552438735961914,
                -6.336615085601807,
                -7.081929683685303,
                -2.8285939693450928,
                0.40311720967292786,
                -5.173876762390137,
                -1.2634074687957764,
                -2.1181275844573975,
                -4.047330856323242,
                2.8961732387542725,
                -3.346149444580078
            ]
        ],
        "y": [
            [
                -0.7048623561859131,
                0.7624332904815674,
                3.0993289947509766,
                7.6577301025390625,
                -4.667094707489014,
                -0.8959536552429199,
                0.3291302025318146,
                -0.9156041741371155,
                -0.9009574055671692,
                -1.561362862586975,
                -0.3371152877807617,
                0.21757109463214874,
                -0.10251877456903458,
                -1.4254207611083984,
                -0.8104364275932312,
                0.42468923330307007,
                0.2638705372810364,
                1.541560411453247,
                0.4466015100479126,
                -0.6107271909713745,
                0.6649693846702576,
                -0.1461494266986847,
                -0.6047363877296448,
                -1.4175300598144531,
                -4.84054708480835,
                -3.53739070892334,
                1.7752732038497925,
                -1.4187757968902588,
                -0.4916175901889801,
                4.938243865966797,
                4.051944732666016,
                1.6721644401550293,
                3.264197826385498,
                -2.923346996307373,
                -0.255738228559494,
                -2.5110585689544678,
                -1.6353726387023926,
                0.12213282287120819,
                1.8241389989852905
            ],
            [
                -0.7866512537002563,
                0.7142148017883301,
                3.0672056674957275,
                7.640036106109619,
                -4.6911115646362305,
                -0.8476026654243469,
                0.3374060094356537,
                -0.882777214050293,
                -0.8186468482017517,
                -1.5325360298156738,
                -0.24671608209609985,
                0.2590746283531189,
                -0.08505325019359589,
                -1.4685016870498657,
                -0.8309569954872131,
                0.3789485692977905,
                0.26657620072364807,
                1.5621451139450073,
                0.4079083800315857,
                -0.6085168123245239,
                0.6896181702613831,
                -0.1542830467224121,
                -0.6239143013954163,
                -1.4395301342010498,
                -4.914892196655273,
                -3.5883984565734863,
                1.7523508071899414,
                -1.483743667602539,
                -0.39988717436790466,
                4.470238208770752,
                2.895609140396118,
                1.965055227279663,
                2.7354342937469482,
                -2.824212074279785,
                -0.19205401837825775,
                -2.5827043056488037,
                -1.7248402833938599,
                0.23006634414196014,
                1.916500449180603
            ],
            [
                -0.779546856880188,
                0.6923150420188904,
                3.0655994415283203,
                7.6426472663879395,
                -4.755146026611328,
                -0.8913373947143555,
                0.31667056679725647,
                -0.8956732153892517,
                -0.7342979907989502,
                -1.4719018936157227,
                -0.1404658406972885,
                0.35228464007377625,
                -0.05631915107369423,
                -1.559799075126648,
                -0.9027804136276245,
                0.3261875510215759,
                0.2579001784324646,
                1.5810556411743164,
                0.44452396035194397,
                -0.6449141502380371,
                0.6852884888648987,
                -0.11314406991004944,
                -0.6679850816726685,
                -1.4602688550949097,
                -4.979602813720703,
                -3.5682430267333984,
                1.7445744276046753,
                -1.506539225578308,
                -0.5012455582618713,
                4.376482963562012,
                3.895596504211426,
                1.7167341709136963,
                2.6353728771209717,
                -2.9158875942230225,
                -0.34046658873558044,
                -2.583970308303833,
                -1.7338393926620483,
                0.22876137495040894,
                1.8483918905258179
            ]
        ],
        "tmit": [
            [
                0.7828882932662964,
                0.9207273721694946,
                0.9060072898864746,
                0.9408432245254517,
                0.964333713054657,
                0.8247510194778442,
                0.9321871995925903,
                0.6027304530143738,
                0.9002236723899841,
                1.389841079711914,
                0.8516334295272827,
                1.3770450353622437,
                1.8347060680389404,
                0.9170430898666382,
                0.9811661839485168,
                0.9113003015518188,
                0.7112809419631958,
                0.9007654190063477,
                0.7473847270011902,
                0.550080418586731,
                0.5168049931526184,
                0.5284676551818848,
                0.47359928488731384,
                0.43748122453689575,
                0.06956472992897034,
                0.17130030691623688,
                0.1913788765668869,
                0.19485798478126526,
                0.18955525755882263,
                0.17402490973472595,
                0.22060881555080414,
                0.7135815620422363,
                0.26377925276756287,
                0.29321610927581787,
                0.15596698224544525,
                0.07366111129522324,
                0.16170069575309753,
                0.14759743213653564,
                0.1673336923122406
            ],
            [
                0.7738267779350281,
                0.907827615737915,
                0.8957563638687134,
                0.9298783540725708,
                0.9550106525421143,
                0.8152283430099487,
                0.9228588342666626,
                0.5985289812088013,
                0.8920135498046875,
                1.3806480169296265,
                0.8423682451248169,
                1.3495157957077026,
                1.8222543001174927,
                0.9087175726890564,
                0.969121515750885,
                0.9009276628494263,
                0.7049009799957275,
                0.8909507989883423,
                0.7369658946990967,
                0.5444521903991699,
                0.5112594962120056,
                0.523474931716919,
                0.4669756591320038,
                0.42973077297210693,
                0.06656427681446075,
                0.16248869895935059,
                0.18461139500141144,
                0.18539105355739594,
                0.18408407270908356,
                0.1700681447982788,
                0.21092258393764496,
                0.6882628798484802,
                0.24029245972633362,
                0.2887672185897827,
                0.15351471304893494,
                0.07032498717308044,
                0.15336179733276367,
                0.14150743186473846,
                0.15915293991565704
            ],
            [
                0.7315506339073181,
                0.8643426895141602,
                0.8519620895385742,
                0.885828971862793,
                0.9105414748191833,
                0.7784634828567505,
                0.8814799189567566,
                0.5773597359657288,
                0.8555347323417664,
                1.340183973312378,
                0.8098015189170837,
                1.3076750040054321,
                1.7780747413635254,
                0.8669697046279907,
                0.9301557540893555,
                0.855838418006897,
                0.6749233603477478,
                0.8480495810508728,
                0.7067095041275024,
                0.5266576409339905,
                0.4903825521469116,
                0.49884480237960815,
                0.4431305527687073,
                0.4084170460700989,
                0.06630337238311768,
                0.16232626140117645,
                0.18350030481815338,
                0.18608587980270386,
                0.18311141431331635,
                0.17114727199077606,
                0.213601753115654,
                0.6807211637496948,
                0.2436477094888687,
                0.27378740906715393,
                0.1455715000629425,
                0.06976175308227539,
                0.15330901741981506,
                0.14145581424236298,
                0.15854446589946747
            ]
        ]
    },
    "icts": {
        "names": [
            "gun:GUNcharge",
            "l0:L0charge",
            "linacbt:LNEcharge",
            "linacbt:BTMcharge",
            "ext:EXTcharge",
            "linacbt:BTEcharge",
            "BIM:DR:nparticles",
            "BIM:IP:nparticles"
        ],
        "charge": [
            0.515127678575,
            0.5636976137499999,
            0.39886249999999995,
            0.28043250000000003,
            0.01835682536333333,
            0.23285145833333332,
            0.006281048525124788,
            -0.0065079680643975735
        ]
    },
    "hcorrectors_names": [
        "ZH1L",
        "ZH2L",
        "ZH3L",
        "ZH4L",
        "ZH5L",
        "ZH6L",
        "ZH7L",
        "ZH8L",
        "ZH9L",
        "ZH10L",
        "ZH11L",
        "ZH12L",
        "ZH30T",
        "ZH40T",
        "ZH50T"
    ],
    "vcorrectors_names": [
        "ZV1L",
        "ZV2L",
        "ZV3L",
        "ZV4L",
        "ZV5L",
        "ZV6L",
        "ZV7L",
        "ZV8L",
        "ZV9L",
        "ZV10L",
        "ZV11L",
        "ZV12L",
        "ZV13L",
        "ZV30T",
        "ZV40T",
        "ZV50T",
        "ZV51T"
    ],
    "timestamp": "2024/05/24, 15:09:53"
}