{
    "sequence": [
        "MB5L",
        "MB6L",
        "MB7L",
        "ZH1L",
        "ZV1L",
        "MB8L",
        "MB9L",
        "MB10L",
        "ZV2L",
        "ZH2L",
        "MB11L",
        "ML1L",
        "ML2L",
        "ZV3L",
        "ZH3L",
        "ML3L",
        "ZH4L",
        "ZV4L",
        "ZH5L",
        "ZV5L",
        "ML4L",
        "ZH6L",
        "ZV6L",
        "ML5L",
        "ZH7L",
        "ZV7L",
        "ML6L",
        "ZH8L",
        "ZV8L",
        "ML7L",
        "ZH9L",
        "ML8L",
        "ZV9L",
        "ML9L",
        "ZH10L",
        "ML10L",
        "ZV10L",
        "ML11L",
        "ZH11L",
        "ML12L",
        "ZV11L",
        "ML13L",
        "ZH12L",
        "ML14L",
        "ZV12L",
        "ML15L",
        "ZX10T",
        "ZX11T",
        "ML1T",
        "ZV13L",
        "ZX12T",
        "ML2T",
        "ZY20T",
        "ZY21T",
        "ML101T",
        "ML102T",
        "ZY22T",
        "ZY23T",
        "ML103T",
        "ZX30T",
        "ML3T",
        "ZX31T",
        "ZV30T",
        "ZH30T",
        "ML104T",
        "ZX32T",
        "ML4T",
        "ML105T",
        "ZV40T",
        "ZH40T",
        "ML5T",
        "ML6T",
        "ZX50T",
        "ML106T",
        "ZX50T",
        "ML7T",
        "ZX51T",
        "ZV50T",
        "ML8T",
        "ZH50T",
        "ZV51T",
        "ML9T",
        "MB10T",
        "MB11T"
    ],
    "correctors": {
        "names": [
            "ZH1L",
            "ZV1L",
            "ZV2L",
            "ZH2L",
            "ZV3L",
            "ZH3L",
            "ZH4L",
            "ZV4L",
            "ZH5L",
            "ZV5L",
            "ZH6L",
            "ZV6L",
            "ZH7L",
            "ZV7L",
            "ZH8L",
            "ZV8L",
            "ZH9L",
            "ZV9L",
            "ZH10L",
            "ZV10L",
            "ZH11L",
            "ZV11L",
            "ZH12L",
            "ZV12L",
            "ZX10T",
            "ZX11T",
            "ZV13L",
            "ZX12T",
            "ZY20T",
            "ZY21T",
            "ZY22T",
            "ZY23T",
            "ZX30T",
            "ZX31T",
            "ZV30T",
            "ZH30T",
            "ZX32T",
            "ZV40T",
            "ZH40T",
            "ZX50T",
            "ZX50T",
            "ZX51T",
            "ZV50T",
            "ZH50T",
            "ZV51T"
        ],
        "bdes": [
            1.6058,
            0.32324,
            -3.694e-05,
            0.05,
            -0.018255,
            -0.0023425,
            -0.63212,
            -0.51377,
            0.0067611,
            0.025597,
            -0.089344,
            -0.23399,
            -0.34279,
            0.0008922,
            0.095066,
            -0.1336,
            -0.39271,
            -0.072191,
            -0.21644,
            -0.41065,
            0.09808,
            0.37969,
            0.043499,
            -0.9134861294990632,
            -0.5,
            0.81,
            -0.69,
            0.9,
            0.34,
            -0.25,
            -1.26,
            -1.47,
            0.0,
            0.0,
            0.09,
            -1.79,
            2.05,
            -1.5,
            -2.1085,
            1.29,
            1.29,
            -1.7,
            0.38,
            1.35,
            0.08
        ],
        "bact": [
            1.6047874689102173,
            0.3224230408668518,
            -0.00488519761711359,
            0.04885197803378105,
            -0.02198338881134987,
            -0.00488519761711359,
            -0.6350756883621216,
            -0.5178309679031372,
            0.00488519761711359,
            0.024425989016890526,
            -0.09281875938177109,
            -0.23693208396434784,
            -0.3468490242958069,
            0.0,
            0.09281875938177109,
            -0.13678553700447083,
            -0.39570102095603943,
            -0.07572057098150253,
            -0.21983389556407928,
            -0.4152418076992035,
            0.0977039560675621,
            0.3786028325557709,
            0.04152418300509453,
            -0.9159745573997498,
            -0.5080605745315552,
            0.8036150336265564,
            -0.6985832452774048,
            0.898876428604126,
            0.33463606238365173,
            -0.2589154839515686,
            -1.2677088975906372,
            -1.4802148342132568,
            0.0,
            0.0,
            0.08304836601018906,
            -1.797752857208252,
            2.044455051422119,
            -1.5095261335372925,
            -2.1128480434417725,
            1.2848069667816162,
            1.2848069667816162,
            -1.7073765993118286,
            0.37371763586997986,
            1.343429446220398,
            0.07572057098150253
        ]
    },
    "bpms": {
        "names": [
            "MB5L",
            "MB6L",
            "MB7L",
            "MB8L",
            "MB9L",
            "MB10L",
            "MB11L",
            "ML1L",
            "ML2L",
            "ML3L",
            "ML4L",
            "ML5L",
            "ML6L",
            "ML7L",
            "ML8L",
            "ML9L",
            "ML10L",
            "ML11L",
            "ML12L",
            "ML13L",
            "ML14L",
            "ML15L",
            "ML1T",
            "ML2T",
            "ML101T",
            "ML102T",
            "ML103T",
            "ML3T",
            "ML104T",
            "ML4T",
            "ML105T",
            "ML5T",
            "ML6T",
            "ML106T",
            "ML7T",
            "ML8T",
            "ML9T",
            "MB10T",
            "MB11T"
        ],
        "x": [
            [
                -1.1923251152038574,
                0.7742019295692444,
                0.18382203578948975,
                -7.934528827667236,
                1.4621590375900269,
                1.1659609079360962,
                0.006601213943213224,
                -2.4464499950408936,
                -0.8748229146003723,
                0.3499124050140381,
                -0.22038497030735016,
                -0.4141790568828583,
                0.5578814148902893,
                -1.1967073678970337,
                0.40129339694976807,
                -6.354681015014648,
                -2.8381965160369873,
                -0.7015401721000671,
                -0.9966220855712891,
                -0.25586557388305664,
                -0.4010661244392395,
                -0.9636631608009338,
                -6.458799839019775,
                1.897515892982483,
                -3.738142728805542,
                1.1953086853027344,
                0.9983393549919128,
                -0.030574452131986618,
                0.16245822608470917,
                -4.546973705291748,
                -6.59328031539917,
                -2.6504433155059814,
                0.6909586191177368,
                -4.439455032348633,
                -0.594443678855896,
                -1.7897758483886719,
                -3.021921157836914,
                2.1223926544189453,
                -3.087268829345703
            ],
            [
                -1.1931331157684326,
                0.7215877771377563,
                0.09740836918354034,
                -7.96339225769043,
                1.443941593170166,
                1.1653987169265747,
                0.012072890996932983,
                -2.382154941558838,
                -0.8896138668060303,
                0.33494359254837036,
                -0.23657220602035522,
                -0.39156314730644226,
                0.5585482120513916,
                -1.21833074092865,
                0.37926679849624634,
                -6.369792461395264,
                -2.8824143409729004,
                -0.6965247392654419,
                -0.9748633503913879,
                -0.20292928814888,
                -0.3159935474395752,
                -0.8985881209373474,
                -6.459817409515381,
                1.7779191732406616,
                -3.8628430366516113,
                1.241607666015625,
                1.0133720636367798,
                -0.15484994649887085,
                0.06341595947742462,
                -4.730244159698486,
                -6.622315883636475,
                -2.745924234390259,
                1.6416819095611572,
                -4.540136814117432,
                -0.6824278831481934,
                -1.797698974609375,
                -3.142146348953247,
                2.2226037979125977,
                -3.137624502182007
            ],
            [
                -1.1652381420135498,
                0.6845691800117493,
                0.15871621668338776,
                -7.9115495681762695,
                1.4943950176239014,
                1.205233097076416,
                0.03969024121761322,
                -2.4011588096618652,
                -0.9214656949043274,
                0.2714848518371582,
                -0.23346637189388275,
                -0.4654507339000702,
                0.5571635961532593,
                -1.268588900566101,
                0.374779611825943,
                -6.3495402336120605,
                -2.8455302715301514,
                -0.707223117351532,
                -0.9745383858680725,
                -0.19283322989940643,
                -0.3297707438468933,
                -0.9297459125518799,
                -6.4319281578063965,
                2.067640781402588,
                -3.685328483581543,
                1.1955453157424927,
                0.9072350263595581,
                0.024196965619921684,
                0.22384008765220642,
                -4.4029364585876465,
                -6.5648417472839355,
                -2.6981661319732666,
                0.9430680871009827,
                -4.315914154052734,
                -0.5170552730560303,
                -1.7695443630218506,
                -3.0153565406799316,
                2.1329565048217773,
                -3.1560051441192627
            ]
        ],
        "y": [
            [
                -0.762600839138031,
                0.6533593535423279,
                3.005098819732666,
                7.584890842437744,
                -4.737419605255127,
                -0.8228732347488403,
                0.40450313687324524,
                -0.8707443475723267,
                -0.8353433012962341,
                -1.5407503843307495,
                -0.2750093638896942,
                0.26943331956863403,
                -0.06188872084021568,
                -1.3519898653030396,
                -0.8386549353599548,
                0.27634426951408386,
                0.1669914424419403,
                1.4086740016937256,
                0.36955857276916504,
                -0.6940796971321106,
                0.6987031102180481,
                0.020238643512129784,
                -0.31229570508003235,
                -1.2814267873764038,
                -5.715907573699951,
                -4.397449493408203,
                2.7179811000823975,
                -1.8852261304855347,
                1.291098952293396,
                5.113579273223877,
                4.658897399902344,
                1.5166321992874146,
                1.2646816968917847,
                -4.022650241851807,
                -2.0107851028442383,
                -3.4003796577453613,
                -2.9425666332244873,
                0.44331327080726624,
                -0.16007155179977417
            ],
            [
                -0.787616491317749,
                0.7245301604270935,
                3.0876474380493164,
                7.6459784507751465,
                -4.6886372566223145,
                -0.8636171221733093,
                0.3274003863334656,
                -0.8752330541610718,
                -0.7755190134048462,
                -1.500406265258789,
                -0.2032826989889145,
                0.3236874043941498,
                -0.03287218511104584,
                -1.3570328950881958,
                -0.8650354743003845,
                0.21729783713817596,
                0.18999424576759338,
                1.3734334707260132,
                0.33658158779144287,
                -0.6755582094192505,
                0.6677600145339966,
                0.04431688040494919,
                -0.28135946393013,
                -1.2859606742858887,
                -5.764089584350586,
                -4.4525980949401855,
                2.8029544353485107,
                -1.9033311605453491,
                1.337708592414856,
                5.333978176116943,
                4.375052452087402,
                1.6094841957092285,
                1.8149487972259521,
                -4.032079219818115,
                -1.974247932434082,
                -3.44986629486084,
                -2.9976449012756348,
                0.3861464262008667,
                -0.21564574539661407
            ],
            [
                -0.7700100541114807,
                0.764789879322052,
                3.1284122467041016,
                7.698813438415527,
                -4.6691131591796875,
                -0.8945368528366089,
                0.28721877932548523,
                -0.9192614555358887,
                -0.7835924625396729,
                -1.5061872005462646,
                -0.1678684651851654,
                0.3392028510570526,
                -0.03935334458947182,
                -1.3478668928146362,
                -0.8470357060432434,
                0.2305079698562622,
                0.08083382993936539,
                1.3841303586959839,
                0.3760107457637787,
                -0.7118562459945679,
                0.663631021976471,
                0.027229569852352142,
                -0.26063501834869385,
                -1.292244553565979,
                -5.737722873687744,
                -4.445194244384766,
                2.781688928604126,
                -1.8867549896240234,
                1.3710699081420898,
                5.192798614501953,
                4.51478385925293,
                1.5686484575271606,
                1.2720792293548584,
                -4.102755546569824,
                -2.1451125144958496,
                -3.424940347671509,
                -3.0081465244293213,
                0.485549658536911,
                -0.2714243531227112
            ]
        ],
        "tmit": [
            [
                0.757308840751648,
                0.892604649066925,
                0.8808602690696716,
                0.9157804250717163,
                0.9403277635574341,
                0.8026124238967896,
                0.9083188772201538,
                0.5900942087173462,
                0.8771272301673889,
                1.3690961599349976,
                0.8324361443519592,
                1.3500562906265259,
                1.8099943399429321,
                0.8949311971664429,
                0.9592521786689758,
                0.8916134238243103,
                0.6909669041633606,
                0.8813031911849976,
                0.7349671721458435,
                0.5408064126968384,
                0.5060175061225891,
                0.5170698165893555,
                0.4534760117530823,
                0.4295597970485687,
                0.11100568622350693,
                0.24630038440227509,
                0.2802654802799225,
                0.28084197640419006,
                0.26542234420776367,
                0.22923949360847473,
                0.2511100769042969,
                0.8024661540985107,
                0.3771124482154846,
                0.2856135666370392,
                0.15234188735485077,
                0.1101418137550354,
                0.22044241428375244,
                0.20741364359855652,
                0.23122476041316986
            ],
            [
                0.7580075263977051,
                0.8952561616897583,
                0.8838521838188171,
                0.9181197285652161,
                0.9404039978981018,
                0.8046817779541016,
                0.9098060727119446,
                0.5919836759567261,
                0.8779472708702087,
                1.3702692985534668,
                0.8340161442756653,
                1.3517630100250244,
                1.8073618412017822,
                0.8917208909988403,
                0.9582486748695374,
                0.8950003981590271,
                0.6889476776123047,
                0.8805158138275146,
                0.7353771924972534,
                0.5427931547164917,
                0.5074593424797058,
                0.5173438191413879,
                0.4550531208515167,
                0.42796412110328674,
                0.10974463075399399,
                0.24065610766410828,
                0.2736999988555908,
                0.2743280529975891,
                0.2608630359172821,
                0.22600215673446655,
                0.25234663486480713,
                0.7997726798057556,
                0.31373530626296997,
                0.2855009436607361,
                0.15191540122032166,
                0.10905865579843521,
                0.21748684346675873,
                0.20405898988246918,
                0.22743861377239227
            ],
            [
                0.7586706876754761,
                0.8934940099716187,
                0.8824700713157654,
                0.9171664714813232,
                0.9389939308166504,
                0.8047239780426025,
                0.9099527597427368,
                0.5917972922325134,
                0.876502513885498,
                1.3691952228546143,
                0.83162522315979,
                1.3433918952941895,
                1.8058252334594727,
                0.8912091255187988,
                0.9572017192840576,
                0.8930952548980713,
                0.6922112703323364,
                0.8761957287788391,
                0.7324010133743286,
                0.538939356803894,
                0.5037256479263306,
                0.5149206519126892,
                0.45095276832580566,
                0.427679181098938,
                0.11387568712234497,
                0.2510513365268707,
                0.2861239016056061,
                0.28787702322006226,
                0.27174460887908936,
                0.2349947839975357,
                0.25873541831970215,
                0.8412521481513977,
                0.37972208857536316,
                0.2842620015144348,
                0.1517021805047989,
                0.11278471350669861,
                0.22624796628952026,
                0.21236823499202728,
                0.23541656136512756
            ]
        ]
    },
    "icts": {
        "names": [
            "gun:GUNcharge",
            "l0:L0charge",
            "linacbt:LNEcharge",
            "linacbt:BTMcharge",
            "ext:EXTcharge",
            "linacbt:BTEcharge",
            "BIM:DR:nparticles",
            "BIM:IP:nparticles"
        ],
        "charge": [
            0.53905402989,
            0.58491811375,
            0.416648125,
            0.3733,
            0.2772569604758333,
            0.3216542361111111,
            0.2596393823623657,
            0.2562178075313568
        ]
    },
    "hcorrectors_names": [
        "ZH1L",
        "ZH2L",
        "ZH3L",
        "ZH4L",
        "ZH5L",
        "ZH6L",
        "ZH7L",
        "ZH8L",
        "ZH9L",
        "ZH10L",
        "ZH11L",
        "ZH12L",
        "ZH30T",
        "ZH40T",
        "ZH50T"
    ],
    "vcorrectors_names": [
        "ZV1L",
        "ZV2L",
        "ZV3L",
        "ZV4L",
        "ZV5L",
        "ZV6L",
        "ZV7L",
        "ZV8L",
        "ZV9L",
        "ZV10L",
        "ZV11L",
        "ZV12L",
        "ZV13L",
        "ZV30T",
        "ZV40T",
        "ZV50T",
        "ZV51T"
    ],
    "timestamp": "2024/05/24, 15:08:32"
}